rrview/__init__.py
rrview/__init__.pyc
rrview/annotation.pyc
rrview/client_report.pyc
rrview/config.pyc
rrview/contrast.pyc
rrview/display.pyc
rrview/helper.pyc
rrview/image_processing.pyc
rrview/install_shortcut.pyc
rrview/main.pyc
rrview/modality_showing.pyc
rrview/my_widgets.pyc
rrview/__pycache__/__init__.cpython-311.pyc
rrview-0.8.2.dist-info/LICENSE
rrview-0.8.2.dist-info/METADATA
rrview-0.8.2.dist-info/WHEEL
rrview-0.8.2.dist-info/entry_points.txt
rrview-0.8.2.dist-info/top_level.txt
rrview-0.8.2.dist-info/RECORD
