Metadata-Version: 2.1
Name: rrview
Version: 0.8.2
Summary: Ruijin Radiology Viewer
Home-page: http://ruijin-imit.cn/software/rrview
Author: Fakai Wang
Author-email: Fakai Wang <fakaiwang@sjtu.edu.cn>
Maintainer-email: Fakai Wang <fakaiwang@sjtu.edu.cn>
Project-URL: Homepage, http://ruijin-imit.cn/software/rrview
Project-URL: Documentation, http://ruijin-imit.cn/software/rrview/docs
Project-URL: Repository, https://github.com/ruijin-imit/rrview.git
Project-URL: Bug Tracker, https://github.com/ruijin-imit/rrview/issues
Project-URL: Changelog, https://github.com/ruijin-imit/rrview/blob/master/CHANGELOG.md
Keywords: Radiology,NifTi,3D Medical Imaging,Multi-modality,Segmentation Mask
Classifier: Development Status :: 4 - Beta
Classifier: Programming Language :: Python
Requires-Python: >=3.6
License-File: LICENSE
Requires-Dist: requests >=2.5.1
Requires-Dist: SimpleITK >=2.2.0
Requires-Dist: PySide6 >=6.7
Requires-Dist: numpy >=1.25.0
Requires-Dist: opencv-python-headless >=4.8.0.76
Requires-Dist: psutil >=7.0.0
Requires-Dist: scipy >=1.15.0
Requires-Dist: setuptools >=68.0.0
Requires-Dist: scikit-image >=0.25.2
Requires-Dist: nibabel >=5.3.2
Provides-Extra: cli
Requires-Dist: rich ; extra == 'cli'
Requires-Dist: click ; extra == 'cli'
Provides-Extra: dev
Requires-Dist: pytest >=6.0 ; extra == 'dev'
Requires-Dist: black >=21.0 ; extra == 'dev'
Provides-Extra: gui
Requires-Dist: PySide6 ; extra == 'gui'
